raspberryrequest/__init__.py
raspberryrequest/backoff.py
raspberryrequest/exceptions.py
raspberryrequest/main.py
raspberryrequest/models.py
raspberryrequest/request.py
raspberryrequest/validate.py
test/__init__.py
test/test_backoff.py
test/test_main.py
test/test_request.py
test/test_validate.py
raspberryrequest-1.1.1.dist-info/METADATA
raspberryrequest-1.1.1.dist-info/WHEEL
raspberryrequest-1.1.1.dist-info/top_level.txt
raspberryrequest-1.1.1.dist-info/RECORD
